MANIFEST.in
README.md
requirements.txt
runtests.sh
setup.py
django_docfield_couchdb.egg-info/PKG-INFO
django_docfield_couchdb.egg-info/SOURCES.txt
django_docfield_couchdb.egg-info/dependency_links.txt
django_docfield_couchdb.egg-info/requires.txt
django_docfield_couchdb.egg-info/top_level.txt
docfield/__init__.py
docfield/modelfields.py
docfield/models.py
docfield/run.py
docfield/settings.py
docfield/tests.py